console_utils/__init__.py
console_utils/utils/calendar_date.py
console_utils/utils/selector.py
console_utils-0.0.10.dist-info/LICENSE
console_utils-0.0.10.dist-info/METADATA
console_utils-0.0.10.dist-info/WHEEL
console_utils-0.0.10.dist-info/top_level.txt
console_utils-0.0.10.dist-info/RECORD
