Metadata-Version: 2.1
Name: console-utils
Version: 0.0.10
Summary: Utilites for that improves console inputs
Author-email: Dilmurod <lador.org@gmail.com>
License: Copyright (c) 2018 The Python Packaging Authority        
Project-URL: Homepage, https://github.com/softskate/console-utils
Project-URL: Bug Tracker, https://github.com/softskate/console-utils/issues
Classifier: Programming Language :: Python :: 3
Classifier: License :: OSI Approved :: MIT License
Classifier: Operating System :: OS Independent
Requires-Python: >=3.7
License-File: LICENSE
